polygraphy_trtexec/__init__.py
polygraphy_trtexec/export.py
polygraphy_trtexec/args/__init__.py
polygraphy_trtexec/args/runner.py
polygraphy_trtexec/backend/__init__.py
polygraphy_trtexec/backend/runner.py
polygraphy_trtexec-0.0.9.dist-info/LICENSE.txt
polygraphy_trtexec-0.0.9.dist-info/METADATA
polygraphy_trtexec-0.0.9.dist-info/WHEEL
polygraphy_trtexec-0.0.9.dist-info/entry_points.txt
polygraphy_trtexec-0.0.9.dist-info/top_level.txt
polygraphy_trtexec-0.0.9.dist-info/zip-safe
polygraphy_trtexec-0.0.9.dist-info/RECORD
