Metadata-Version: 2.1
Name: polygraphy-trtexec
Version: 0.0.9
Summary: Polygraphy Trtexec: Extension to run on trtexec backend
Home-page: https://github.com/NVIDIA/TensorRT/tree/main/tools/Polygraphy
Author: NVIDIA
Author-email: svc_tensorrt@nvidia.com
License: Apache 2.0
Platform: UNKNOWN
Classifier: Intended Audience :: Developers
Classifier: Programming Language :: Python :: 3
Requires-Python: >=3.6
License-File: LICENSE.txt
Requires-Dist: polygraphy (>=0.49.0)
